casing/__init__.py
casing/casing.py
casing/check.py
casing-1.0.12.dist-info/LICENSE
casing-1.0.12.dist-info/WHEEL
casing-1.0.12.dist-info/METADATA
casing-1.0.12.dist-info/RECORD
