Metadata-Version: 2.1
Name: casing
Version: 1.0.12
Summary: Easy casing nomenclatures management such as camelCase, snake_case and many others!
Author: vincentBenet
Author-email: vincent.benet@outlook.fr
Requires-Python: >=3.6,<4.0
Classifier: Programming Language :: Python :: 3
Classifier: Programming Language :: Python :: 3.6
Classifier: Programming Language :: Python :: 3.7
Classifier: Programming Language :: Python :: 3.8
Classifier: Programming Language :: Python :: 3.9
Classifier: Programming Language :: Python :: 3.10
Classifier: Programming Language :: Python :: 3.11
